redis_bulk_cleaner/__init__.py
redis_bulk_cleaner/__main__.py
redis_bulk_cleaner/cli.py
redis_bulk_cleaner/redis_bulk_cleaner.py
redis_bulk_cleaner-0.1.5.dist-info/LICENSE
redis_bulk_cleaner-0.1.5.dist-info/METADATA
redis_bulk_cleaner-0.1.5.dist-info/WHEEL
redis_bulk_cleaner-0.1.5.dist-info/entry_points.txt
redis_bulk_cleaner-0.1.5.dist-info/top_level.txt
redis_bulk_cleaner-0.1.5.dist-info/RECORD
