Metadata-Version: 2.1
Name: redis-bulk-cleaner
Version: 0.1.5
Summary: 
Home-page: https://github.com/bogdandm/redis_bulk_cleaner
Author: Bogdan Kalashnikov
Author-email: bogdan.dm@gmail.com
License: MIT license
Keywords: redis_bulk_cleaner
Platform: UNKNOWN
Classifier: Intended Audience :: Developers
Classifier: License :: OSI Approved :: MIT License
Classifier: Programming Language :: Python :: 3
Classifier: Programming Language :: Python :: 3.5
Classifier: Programming Language :: Python :: 3.6
Classifier: Programming Language :: Python :: 3.7
Classifier: Programming Language :: Python :: 3.8
Requires-Python: >=3.5
Requires-Dist: Click (>=7.0)
Requires-Dist: redis (>=3.0)
Requires-Dist: tqdm (>=4.30.0)
